endjoy.py
endjoy-1.0.0.dist-info/entry_points.txt
endjoy-1.0.0.dist-info/LICENSE
endjoy-1.0.0.dist-info/WHEEL
endjoy-1.0.0.dist-info/METADATA
endjoy-1.0.0.dist-info/RECORD
