Metadata-Version: 2.1
Name: endjoy
Version: 1.0.0
Summary: Ctrl-Z for the filesystem
Home-page: https://github.com/corollari/endjoy
License: Unlicense
Author: Albert
Author-email: github@albert.sh
Requires-Python: >=3.5,<4.0
Classifier: License :: Other/Proprietary License
Classifier: Programming Language :: Python :: 3
Classifier: Programming Language :: Python :: 3.5
Classifier: Programming Language :: Python :: 3.6
Classifier: Programming Language :: Python :: 3.7
Requires-Dist: inotify (>=0.2.10,<0.3.0)
Project-URL: Repository, https://github.com/corollari/endjoy
